clinical_research_study_manager/__init__.py
clinical_research_study_manager/add_patient_to_excel_file.py
clinical_research_study_manager/create_directories.py
clinical_research_study_manager/create_excel_files.py
clinical_research_study_manager/data_request_functions.py
clinical_research_study_manager/enrollment_queries.py
clinical_research_study_manager/enter_patient_on_log.py
clinical_research_study_manager/exceptions.py
clinical_research_study_manager/follow_up_queries.py
clinical_research_study_manager/generate_fake_data.py
clinical_research_study_manager/get_data_from_user.py
clinical_research_study_manager/load_project.py
clinical_research_study_manager/screening_queries.py
clinical_research_study_manager/stats_functions.py
clinical_research_study_manager/study_manager.py
clinical_research_study_manager/tests/__init__.py
clinical_research_study_manager/tests/testing_input_types.py
clinical_research_study_manager-1.2.1.dev1.dist-info/DESCRIPTION.rst
clinical_research_study_manager-1.2.1.dev1.dist-info/METADATA
clinical_research_study_manager-1.2.1.dev1.dist-info/RECORD
clinical_research_study_manager-1.2.1.dev1.dist-info/WHEEL
clinical_research_study_manager-1.2.1.dev1.dist-info/metadata.json
clinical_research_study_manager-1.2.1.dev1.dist-info/top_level.txt
