Metadata-Version: 2.0
Name: clinical-research-study-manager
Version: 1.2.1.dev1
Summary: Program to manage some common clinical research tasks from the command line
Home-page: https://github.com/SethPitts/clinical_research_study_manager
Author: Seth Pitts
Author-email: sethpitts22@gmail.com
License: MIT
Keywords: clinical research data management
Platform: UNKNOWN
Classifier: Development Status :: 3 - Alpha
Classifier: Intended Audience :: Developers
Classifier: Topic :: Software Development
Classifier: License :: OSI Approved :: MIT License
Classifier: Programming Language :: Python :: 3
Classifier: Programming Language :: Python :: 3.3
Classifier: Programming Language :: Python :: 3.4
Classifier: Programming Language :: Python :: 3.5
Requires-Dist: pandas
Requires-Dist: openpyxl
Requires-Dist: numpy
Requires-Dist: matplotlib
